wptools/__init__.py
wptools/__main__.py
wptools/category.py
wptools/core.py
wptools/page.py
wptools/query.py
wptools/restbase.py
wptools/site.py
wptools/utils.py
wptools/wikidata.py
wptools/wptool.py
wptools_clone-0.4.22.dist-info/LICENSE
wptools_clone-0.4.22.dist-info/METADATA
wptools_clone-0.4.22.dist-info/WHEEL
wptools_clone-0.4.22.dist-info/entry_points.txt
wptools_clone-0.4.22.dist-info/top_level.txt
wptools_clone-0.4.22.dist-info/RECORD
