Metadata-Version: 2.1
Name: wptools-clone
Version: 0.4.22
Summary: Wikipedia tools (for Humans)
Home-page: https://github.com/ider-zh/wptools
Author: Steve @siznax
Author-email: steve@siznax.net
License: MIT
Classifier: Development Status :: 3 - Alpha
Classifier: Intended Audience :: Developers
Classifier: Intended Audience :: Education
Classifier: Intended Audience :: Science/Research
Classifier: License :: OSI Approved :: MIT License
Classifier: Operating System :: OS Independent
Classifier: Programming Language :: Python
Classifier: Programming Language :: Python :: 2.7
Classifier: Programming Language :: Python :: 3
License-File: LICENSE
Requires-Dist: certifi
Requires-Dist: html2text
Requires-Dist: lxml
